lopc/__init__.py
lopc/__main__.py
lopc/lopc.py
lopc-1.0.2.dist-info/LICENSE.md
lopc-1.0.2.dist-info/METADATA
lopc-1.0.2.dist-info/WHEEL
lopc-1.0.2.dist-info/entry_points.txt
lopc-1.0.2.dist-info/top_level.txt
lopc-1.0.2.dist-info/RECORD
