Metadata-Version: 2.1
Name: lopc
Version: 1.0.2
Summary: Counts lines of Python code
Home-page: https://github.com/markkuleinio/lopc
Author: Markku Leiniö
License: MIT
Requires-Python: >=3.7
License-File: LICENSE.md
